ids_peak_common/__init__.py
ids_peak_common/exceptions.py
ids_peak_common/py.typed
ids_peak_common/_internal/__init__.py
ids_peak_common/_internal/constants.py
ids_peak_common/_internal/utils.py
ids_peak_common/datatypes/__init__.py
ids_peak_common/datatypes/iimageview.py
ids_peak_common/datatypes/interval.py
ids_peak_common/datatypes/metadata.py
ids_peak_common/datatypes/metadata_key.py
ids_peak_common/datatypes/pixelformat.py
ids_peak_common/datatypes/range.py
ids_peak_common/datatypes/geometry/__init__.py
ids_peak_common/datatypes/geometry/point.py
ids_peak_common/datatypes/geometry/rectangle.py
ids_peak_common/datatypes/geometry/size.py
ids_peak_common/pipeline/__init__.py
ids_peak_common/pipeline/ipipeline.py
ids_peak_common/pipeline/pipeline_base.py
ids_peak_common/pipeline/modules/__init__.py
ids_peak_common/pipeline/modules/iautofeature_module.py
ids_peak_common/pipeline/modules/igain_module.py
ids_peak_common/pipeline/modules/imodule.py
ids_peak_common/serialization/__init__.py
ids_peak_common/serialization/iarchive.py
ids_peak_common/serialization/ideserializer.py
ids_peak_common/serialization/iserializable.py
ids_peak_common/serialization/iserializer.py
ids_peak_common-1.1.0.2757.dist-info/licenses/LICENSE
ids_peak_common-1.1.0.2757.dist-info/METADATA
ids_peak_common-1.1.0.2757.dist-info/WHEEL
ids_peak_common-1.1.0.2757.dist-info/top_level.txt
ids_peak_common-1.1.0.2757.dist-info/RECORD
