Metadata-Version: 2.4
Name: ids_peak_common
Version: 1.1.0.2757
Summary: ids_peak_common - Common foundational types and utilities
Author-email: IDS Imaging Development Systems GmbH <support@ids-imaging.com>
Project-URL: Homepage, https://www.ids-imaging.com
Classifier: Programming Language :: Python :: 3
Classifier: Topic :: Multimedia :: Graphics :: Capture :: Digital Camera
Classifier: Topic :: Multimedia :: Video
Classifier: Typing :: Typed
Requires-Python: >=3.10
License-File: LICENSE
Dynamic: license-file
